setup.py
src/SQLAlchemy_Dao.egg-info/PKG-INFO
src/SQLAlchemy_Dao.egg-info/SOURCES.txt
src/SQLAlchemy_Dao.egg-info/dependency_links.txt
src/SQLAlchemy_Dao.egg-info/requires.txt
src/SQLAlchemy_Dao.egg-info/top_level.txt
src/sqlalchemy_dao/__init__.py
src/sqlalchemy_dao/context.py
src/sqlalchemy_dao/dao.py
src/sqlalchemy_dao/errors.py
src/sqlalchemy_dao/lock.py
src/sqlalchemy_dao/model.py
src/sqlalchemy_dao/session.py
src/sqlalchemy_dao/testing.py
test/testing_test.py
test/testutil.py