Metadata-Version: 1.1
Name: SQLAlchemy-Dao
Version: 1.2.3
Summary: Simple wrapper for sqlalchemy.
Home-page: https://package-insights.appspot.com/packages/sqlalchemy-dao
Author: Mengchen LEE
Author-email: CooledCoffee@gmail.com
License: UNKNOWN
Platform: UNKNOWN
Classifier: Development Status :: 4 - Beta
Classifier: Intended Audience :: Developers
Classifier: Operating System :: OS Independent
Classifier: Programming Language :: Python
Classifier: Programming Language :: Python :: 2
Classifier: Topic :: Software Development :: Libraries
